Metadata-Version: 2.1
Name: PyLambdAPI
Version: 0.1.6
Summary: A lightweight API framework for AWS Lambda
Home-page: https://github.com/KushagraIndurkhya/PyLambdAPI
Author: Kushagra Indurkhya
Author-email: kushagraindurkhya7@gmail.com
License: UNKNOWN
Platform: UNKNOWN
License-File: LICENSE
